omdclient/__init__.py
omdclient-1.4.3.data/data/share/man/man1/omd-activate.1
omdclient-1.4.3.data/data/share/man/man1/omd-host-crud.1
omdclient-1.4.3.data/data/share/man/man1/omd-host-tag.1
omdclient-1.4.3.data/data/share/man/man1/omd-nagios-ack.1
omdclient-1.4.3.data/data/share/man/man1/omd-nagios-downtime.1
omdclient-1.4.3.data/data/share/man/man1/omd-nagios-hostlist.1
omdclient-1.4.3.data/data/share/man/man1/omd-nagios-hosts-with-problem.1
omdclient-1.4.3.data/data/share/man/man1/omd-nagios-report.1
omdclient-1.4.3.data/data/share/man/man1/omd-puppet-enc.1
omdclient-1.4.3.data/data/share/man/man1/omd-reinventory.1
omdclient-1.4.3.data/scripts/omd-activate
omdclient-1.4.3.data/scripts/omd-bulkimport
omdclient-1.4.3.data/scripts/omd-host-crud
omdclient-1.4.3.data/scripts/omd-host-report
omdclient-1.4.3.data/scripts/omd-host-tag
omdclient-1.4.3.data/scripts/omd-nagios-ack
omdclient-1.4.3.data/scripts/omd-nagios-downtime
omdclient-1.4.3.data/scripts/omd-nagios-hostlist
omdclient-1.4.3.data/scripts/omd-nagios-hosts-with-problem
omdclient-1.4.3.data/scripts/omd-nagios-report
omdclient-1.4.3.data/scripts/omd-puppet-enc
omdclient-1.4.3.data/scripts/omd-reinventory
omdclient-1.4.3.dist-info/LICENSE
omdclient-1.4.3.dist-info/METADATA
omdclient-1.4.3.dist-info/WHEEL
omdclient-1.4.3.dist-info/top_level.txt
omdclient-1.4.3.dist-info/RECORD
