Metadata-Version: 2.1
Name: omdclient
Version: 1.4.3
Summary: omdclient check_mk + WATO/OMD interface
Home-page: https://github.com/tskirvin/omdclient/
Author: Tim Skirvin
Author-email: tskirvin@fnal.gov
Maintainer: Tim Skirvin
Maintainer-email: tskirvin@fnal.gov
License: Perl Artistic
Keywords: check_mk,omd,nagios,api,wato
Platform: UNKNOWN
